LICENSE
MANIFEST.in
README.rst
setup.cfg
setup.py
versioneer.py
examples/implicit.yaml
examples/simple.yaml
examples/standard.yaml
examples/standard_jinja.yaml
examples/test.yaml
ommprotocol/__init__.py
ommprotocol/_version.py
ommprotocol/analyze.py
ommprotocol/io.py
ommprotocol/md.py
ommprotocol/utils.py
ommprotocol.egg-info/PKG-INFO
ommprotocol.egg-info/SOURCES.txt
ommprotocol.egg-info/dependency_links.txt
ommprotocol.egg-info/entry_points.txt
ommprotocol.egg-info/top_level.txt
ommprotocol/../examples/implicit.yaml
ommprotocol/../examples/simple.yaml
ommprotocol/../examples/standard.yaml
ommprotocol/../examples/standard_jinja.yaml
ommprotocol/../examples/test.yaml