Metadata-Version: 1.1
Name: ommprotocol
Version: 0.1.9
Summary: Easy to deploy MD protocols for OpenMM
Home-page: https://github.com/insilichem/ommprotocol
Author: Jaime Rodríguez-Guerra
Author-email: jaime.rogue@gmail.com
License: LGPL
Download-URL: https://github.com/insilichem/ommprotocol/tarball/v0.1.9
Platform: any
Classifier: Programming Language :: Python
Classifier: Development Status :: 3 - Alpha
Classifier: Natural Language :: English
Classifier: Environment :: Console
Classifier: Intended Audience :: Science/Research
Classifier: License :: OSI Approved :: GNU Library or Lesser General Public License (LGPL)
Classifier: Operating System :: OS Independent
Classifier: Topic :: Scientific/Engineering :: Chemistry
